blincus/__init__.py
blincus/client.py
blincus/exceptions.py
blincus/message.py
blincus/payment.py
blincus/paymentretrieve.py
blincus/refund.py
tests/__init__.py
tests/test_client.py
blincus_test-0.39.dist-info/LICENCE
blincus_test-0.39.dist-info/METADATA
blincus_test-0.39.dist-info/WHEEL
blincus_test-0.39.dist-info/top_level.txt
blincus_test-0.39.dist-info/RECORD
