Metadata-Version: 2.1
Name: blincus-test
Version: 0.39
Summary: A Blincus payment processing and messaging package.
Home-page: https://github.com/nathan2002-hash/test-blincus-python
Author: Quixines
Author-email: nathan@quixines.com
Classifier: Programming Language :: Python :: 3
Classifier: License :: OSI Approved :: MIT License
Classifier: Operating System :: OS Independent
Requires-Python: >=3.6
License-File: LICENCE
Requires-Dist: requests>=2.25.1
